[
    {
        "img_urls": [
            "https://scontent-sin6-2.cdninstagram.com/vp/09633104483a41df5939a815888f159d/5D4116A9/t51.2885-15/e35/55811544_686787375073712_3259953997545709361_n.jpg?_nc_ht=scontent-sin6-2.cdninstagram.com&_nc_cat=108"
        ],
        "hashtags": [
            "realfood",
            "peanutbutter"
        ],
        "comments": [
            {
                "comment": "Justin’s honey and vanilla flavors",
                "author": "lexdemedici"
            },
            {
                "comment": "Just good old crushed peanuts from the WF machines! It’s the most natural. Btw I hope you’re doing well!! Xxx",
                "author": "karinka_mia"
            },
            {
                "comment": "Maranatha smooth almond butter is delish! Good choice",
                "author": "sameden212"
            },
            {
                "comment": "Blue P is my faaaaaav",
                "author": "goofmagoo"
            },
            {
                "comment": "That cinnamon almond butter by PB Love is crack",
                "author": "meganmurphy5280"
            },
            {
                "comment": "I am SO EXCITED to get down with this tomorrow!",
                "author": "csg7210"
            },
            {
                "comment": "Of course this is what you do in your free time",
                "author": "jungleegurl"
            },
            {
                "comment": "@jungleegurl it'd with a purpose I promise",
                "mentions": [
                    "jungleegurl"
                ],
                "author": "pashmina"
            },
            {
                "comment": "@csg7210 me too!!!",
                "mentions": [
                    "csg7210"
                ],
                "author": "lifeellevated"
            },
            {
                "comment": "@lifeellevated what peanut butter do you eat? Need to round this out with WF ground and 365",
                "mentions": [
                    "lifeellevated"
                ],
                "author": "pashmina"
            },
            {
                "comment": "@goofmagoo what is Blue P?",
                "mentions": [
                    "goofmagoo"
                ],
                "author": "pashmina"
            },
            {
                "comment": "@pashmina the salty peanut one from PB love",
                "mentions": [
                    "pashmina"
                ],
                "author": "goofmagoo"
            },
            {
                "comment": "@goofmagoo yesssss!!! My favorite that I'm hoping wins tomorrow 🤩",
                "mentions": [
                    "goofmagoo"
                ],
                "author": "pashmina"
            },
            {
                "comment": "To stuff into chocolate 🍫?!",
                "author": "of_coursen"
            },
            {
                "comment": "@of_coursen potentially...",
                "mentions": [
                    "of_coursen"
                ],
                "author": "pashmina"
            },
            {
                "comment": "PB love Co cinnamon is insanely delicious. 😍 Crack is right. 😂",
                "author": "empoweredkitchen"
            },
            {
                "comment": "Justins",
                "author": "denni_chankleta"
            },
            {
                "comment": "@eatnuttzo all day",
                "mentions": [
                    "eatnuttzo"
                ],
                "author": "rony_mo"
            }
        ],
        "datetime": "2019-04-10T01:50:55.000Z",
        "caption": "Testing out nut butter brands. Going to try and be as objective as possible. What's your favorite? Looking for #realfood #peanutbutter",
        "likes": 9,
        "key": "https://www.instagram.com/p/BwDqWOilXjj/"
    },
    {
        "img_urls": [
            "https://scontent-sin6-2.cdninstagram.com/vp/c86a9c2f5867f5980b0ecc887535c36d/5D4706F3/t51.2885-15/e35/46569182_1161611444004587_9172847617837629440_n.jpg?_nc_ht=scontent-sin6-2.cdninstagram.com&_nc_cat=111"
        ],
        "hashtags": [
            "costarica",
            "magicalsunsets"
        ],
        "comments": [
            {
                "comment": "So glad you’re there!! Let me know if you need any recs!!! xoxo",
                "author": "karinka_mia"
            },
            {
                "comment": "Gorgeous view babe🙌🏽",
                "author": "squ4dmom"
            }
        ],
        "datetime": "2018-11-28T02:05:43.000Z",
        "caption": "#costarica has #magicalsunsets What a great way to spend a week away.",
        "likes": 33,
        "key": "https://www.instagram.com/p/BqtOUNXlqAM/"
    },
    {
        "img_urls": [
            "https://scontent-sin6-2.cdninstagram.com/vp/1ab0990e8b1c40d5a4835e5e428350f6/5D516300/t51.2885-15/e35/42973113_2178864665471135_1866776023031349248_n.jpg?_nc_ht=scontent-sin6-2.cdninstagram.com&_nc_cat=111"
        ],
        "comments": [
            {
                "comment": "So cool, Pash!! Congrats!!",
                "author": "karinka_mia"
            },
            {
                "comment": "Congratulations Pashu ♥️🍾",
                "author": "anju_mua"
            },
            {
                "comment": "👏🏾👏🏾👏🏾",
                "author": "d0lem1te"
            },
            {
                "comment": "We’ll be in Charleston the weekend of Oct. 20! Are you still going to be around?",
                "author": "momarie_"
            },
            {
                "comment": "Awesome! Congratulations!! The most beautiful wall!",
                "author": "faunalikesflora"
            },
            {
                "comment": "Yes!! Congrats!",
                "author": "ourxtraordinarylife"
            },
            {
                "comment": "Congratulations my friend!!!!🙌❤️",
                "author": "ique_ball"
            },
            {
                "comment": "Omg you really did it",
                "author": "omg_its_jennyp"
            },
            {
                "comment": "Amazing!! Congrats!!",
                "author": "dadlanijewels"
            },
            {
                "comment": "Gorgeous!!! Chocolate too. 🙌🏻",
                "author": "kristinlangenfeld"
            },
            {
                "comment": "Congratulations 🎉",
                "author": "juhidaswani"
            },
            {
                "comment": "@momarie_ I'm already home.",
                "mentions": [
                    "momarie_"
                ],
                "author": "pashmina"
            },
            {
                "comment": "Congratulation",
                "author": "sheilalaungani"
            }
        ],
        "datetime": "2018-10-08T12:58:27.000Z",
        "caption": "Our new chocolate wall at @barandcocoa Charleston!",
        "likes": 80,
        "key": "https://www.instagram.com/p/BorEeUSFSa9/",
        "mentions": [
            "barandcocoa"
        ]
    },
    {
        "img_urls": [
            "https://scontent-sin6-2.cdninstagram.com/vp/27b2fc87aeba49f456355d163b772d5c/5D356F51/t51.2885-15/e35/41544235_347056349367334_8997227925522612224_n.jpg?_nc_ht=scontent-sin6-2.cdninstagram.com&_nc_cat=110"
        ],
        "comments": [
            {
                "comment": "Yes...its the best way to experience the islands@",
                "author": "meenaac"
            }
        ],
        "datetime": "2018-09-18T12:40:44.000Z",
        "caption": "Boats on boats. If we come back here a yacht might be the way to go...",
        "likes": 43,
        "key": "https://www.instagram.com/p/Bn3ijGfHPrE/"
    },
    {
        "img_urls": [
            "https://scontent-sin6-2.cdninstagram.com/vp/a7537c0de7c965c13d53cea9d7f6636c/5D3D11AB/t51.2885-15/e35/41677727_2092885900971711_2053567861586132992_n.jpg?_nc_ht=scontent-sin6-2.cdninstagram.com&_nc_cat=103"
        ],
        "hashtags": [
            "greenstreetmarket",
            "croatianfood",
            "wineandcheese"
        ],
        "comments": [
            {
                "comment": "😋 Yummm!!! Hope you’re loving it there! Post more pics!!",
                "author": "kristinlangenfeld"
            },
            {
                "comment": "I’m going there in 2 weeks!",
                "author": "anarae7"
            },
            {
                "comment": "I wanna be there 🙌🏽",
                "author": "squ4dmom"
            }
        ],
        "datetime": "2018-09-17T23:15:30.000Z",
        "caption": "Bae wasn't feeling well today so I made a charcuterie plate at home with ingredients from #greenstreetmarket #croatianfood #wineandcheese",
        "likes": 44,
        "key": "https://www.instagram.com/p/Bn2GZbQnm-f/"
    },
    {
        "img_urls": [
            "https://scontent-sin6-2.cdninstagram.com/vp/e61a66c947c1c63ab103d175c5ff6e0a/5D765660/t51.2885-15/e35/40714550_282779129209658_4530584352840482816_n.jpg?_nc_ht=scontent-sin6-2.cdninstagram.com&_nc_cat=102"
        ],
        "hashtags": [
            "oldcity"
        ],
        "comments": [
            {
                "comment": "Awesome 🙌🏽",
                "author": "squ4dmom"
            }
        ],
        "datetime": "2018-09-15T10:05:27.000Z",
        "caption": "One last look at the #oldcity before driving to Ston for oysters. Dubrovnik was a great way to start our vacation!",
        "likes": 58,
        "key": "https://www.instagram.com/p/BnviZITHw68/"
    },
    {
        "views": 107,
        "img_urls": [
            "https://scontent-sin6-2.cdninstagram.com/vp/6a5e4378021a28bc3cb54dfae6c3441a/5CBD5A07/t51.2885-15/e35/28752780_1804244743203477_2815454369376370688_n.jpg?_nc_ht=scontent-sin6-2.cdninstagram.com&_nc_cat=109"
        ],
        "hashtags": [
            "snorkeling",
            "Galapagos",
            "sealions"
        ],
        "comments": [
            {
                "comment": "This looks like sooo much fun",
                "author": "lexdemedici"
            },
            {
                "comment": "Those guys are mean!",
                "author": "alysa_paige"
            },
            {
                "comment": "Best ever❤️",
                "author": "squ4dmom"
            },
            {
                "comment": "@alysa_paige they were super playful!",
                "mentions": [
                    "alysa_paige"
                ],
                "author": "pashmina"
            }
        ],
        "datetime": "2018-03-05T22:21:23.000Z",
        "caption": "More video of #snorkeling in #Galapagos Ecuador. This time playing with #sealions",
        "likes": 31,
        "key": "https://www.instagram.com/p/Bf9USoSBr_P/"
    },
    {
        "views": 102,
        "img_urls": [
            "https://scontent-sin6-2.cdninstagram.com/vp/aeca6f6cf0a3996b00b76ea77bb7036f/5CBD7A5D/t51.2885-15/e35/28154058_1785857935053175_3114416318317592576_n.jpg?_nc_ht=scontent-sin6-2.cdninstagram.com&_nc_cat=107"
        ],
        "hashtags": [
            "pengeuinophilia",
            "Ecuador",
            "Galapagos",
            "galapagospenguins",
            "penguins",
            "snorkelingadventure",
            "swimmingwithpenguins",
            "experiencesnotthings"
        ],
        "comments": [
            {
                "comment": "How cool!!!!!",
                "author": "karinka_mia"
            },
            {
                "comment": "Are you in Isla Bartolomé?",
                "author": "therealwolfe"
            }
        ],
        "datetime": "2018-03-03T16:59:20.000Z",
        "caption": "Serious #pengeuinophilia #Ecuador #Galapagos #galapagospenguins #penguins #snorkelingadventure #swimmingwithpenguins #experiencesnotthings @lilcmarie_ in the shot too!",
        "likes": 25,
        "key": "https://www.instagram.com/p/Bf3lgKnh6OQ/",
        "mentions": [
            "lilcmarie_"
        ]
    },
    {
        "img_urls": [
            "https://scontent-sin6-2.cdninstagram.com/vp/a54906d547626670169a5daa2c93c6fa/5D560091/t51.2885-15/e35/17077637_275447086220727_1092386762363240448_n.jpg?_nc_ht=scontent-sin6-2.cdninstagram.com&_nc_cat=103"
        ],
        "hashtags": [
            "saintchappelle",
            "stainedglass",
            "wheninparis",
            "architecturelovers"
        ],
        "datetime": "2017-03-02T13:34:28.000Z",
        "caption": "Woah. #saintchappelle #stainedglass #wheninparis #architecturelovers",
        "likes": 16,
        "key": "https://www.instagram.com/p/BRIzkPWBdfQ/"
    },
    {
        "img_urls": [
            "https://scontent-sin6-2.cdninstagram.com/vp/a87cb3845808f61e193f2a790a4d466e/5D3184EB/t51.2885-15/e35/17076137_1908011446096615_7631902369525006336_n.jpg?_nc_ht=scontent-sin6-2.cdninstagram.com&_nc_cat=107"
        ],
        "hashtags": [
            "shessosmall",
            "monalisa",
            "seekart",
            "wheninparis",
            "louvremuseum"
        ],
        "comments": [
            {
                "comment": "This is a great pic!",
                "author": "marisaannm"
            },
            {
                "comment": "wow - amazed there wasn't anyone else around - did you go at 6am or something?",
                "author": "tedforla"
            },
            {
                "comment": "Omg I LOVE this!!!",
                "author": "adventuresofp"
            },
            {
                "comment": "@tedforla the trick is to go on Wed night when they are open late and go around 9p",
                "mentions": [
                    "tedforla"
                ],
                "author": "pashmina"
            }
        ],
        "datetime": "2017-03-01T20:17:27.000Z",
        "caption": "I can stare too you know... #shessosmall #monalisa #seekart #wheninparis #louvremuseum",
        "likes": 29,
        "key": "https://www.instagram.com/p/BRG8471Bwbv/"
    },
    {
        "img_urls": [
            "https://scontent-sin6-2.cdninstagram.com/vp/be61cd41ccc744191ecb5ff65b0c2a79/5D3B3E96/t51.2885-15/e35/17077232_260156944409821_2756408511905660928_n.jpg?_nc_ht=scontent-sin6-2.cdninstagram.com&_nc_cat=101"
        ],
        "hashtags": [
            "theweeknd",
            "nogimmicks",
            "livemusicphotography",
            "livemore",
            "travelmusic"
        ],
        "comments": [
            {
                "comment": "Great pic, Pash!!",
                "author": "karinka_mia"
            },
            {
                "comment": "You look soooooo close!!!!!",
                "author": "hikingbunny32"
            }
        ],
        "datetime": "2017-03-01T15:34:57.000Z",
        "caption": "The Weeknd. Great show. Not too heavy on light effects, great sound, just him, a mic and a spotlight. #theweeknd #nogimmicks #livemusicphotography #livemore #travelmusic",
        "likes": 19,
        "key": "https://www.instagram.com/p/BRGcj2cBbAc/"
    },
    {
        "img_urls": [
            "https://scontent-sin6-2.cdninstagram.com/vp/10ee93b02908d9fa70ee28b6acacb8f6/5D43CF2A/t51.2885-15/e35/15043853_1092440054186756_7908128586962305024_n.jpg?_nc_ht=scontent-sin6-2.cdninstagram.com&_nc_cat=108"
        ],
        "hashtags": [
            "meidforraj"
        ],
        "datetime": "2016-11-18T22:51:14.000Z",
        "caption": "First night. Prayers at home. #meidforraj",
        "likes": 28,
        "key": "https://www.instagram.com/p/BM-AnM7BpGT/"
    },
    {
        "img_urls": [
            "https://scontent-sin6-2.cdninstagram.com/vp/da796d4cd6702ee618dd4e166a149f1e/5D34B6D5/t51.2885-15/e35/14730747_339895729694301_1715518132543553536_n.jpg?_nc_ht=scontent-sin6-2.cdninstagram.com&_nc_cat=109"
        ],
        "hashtags": [
            "chandelier",
            "winecave",
            "swavorski"
        ],
        "comments": [
            {
                "comment": "This is so gorgeous!",
                "author": "scarlett.daisy"
            }
        ],
        "datetime": "2016-10-14T03:04:17.000Z",
        "caption": "The #chandelier to end all chandeliers. Tree root shaped like a vine, in the #winecave with #swavorski crystals",
        "likes": 19,
        "key": "https://www.instagram.com/p/BLhw9EKByNj/"
    },
    {
        "img_urls": [
            "https://scontent-sin6-2.cdninstagram.com/vp/9a805971913ce7a36fdc1d3e11d625b2/5D52C7CA/t51.2885-15/e35/14705086_306506976391202_8170922109497769984_n.jpg?_nc_ht=scontent-sin6-2.cdninstagram.com&_nc_cat=102"
        ],
        "hashtags": [
            "winecountry",
            "winetastings",
            "oldworld",
            "napavalley"
        ],
        "comments": [
            {
                "comment": "Jealous!!! Have so much fun!!! 🍷",
                "author": "kristinlangenfeld"
            }
        ],
        "datetime": "2016-10-12T20:59:17.000Z",
        "caption": "Beautiful way to start the morning. #winecountry #winetastings #oldworld #napavalley",
        "likes": 18,
        "key": "https://www.instagram.com/p/BLeiY0KBXJB/"
    },
    {
        "img_urls": [
            "https://scontent-sin6-2.cdninstagram.com/vp/c2e044f0b638223263b7cea96613ec10/5D46DF1A/t51.2885-15/e35/14566682_817540908399940_1496309117789143040_n.jpg?_nc_ht=scontent-sin6-2.cdninstagram.com&_nc_cat=104"
        ],
        "hashtags": [
            "craterlake",
            "nationalpark"
        ],
        "comments": [
            {
                "comment": "#babe",
                "hashtags": [
                    "babe"
                ],
                "author": "lindsay_is_here"
            },
            {
                "comment": "I'm so jealous! And you look great!",
                "author": "alysa_paige"
            },
            {
                "comment": "Yay. You got there!! Gorgeous!",
                "author": "valeriejoyseid"
            }
        ],
        "datetime": "2016-10-09T21:36:21.000Z",
        "caption": "Detour to check out this beauty real quick. #craterlake #nationalpark",
        "likes": 35,
        "key": "https://www.instagram.com/p/BLW4Pv7BKeu/"
    },
    {
        "img_urls": [
            "https://scontent-sin6-2.cdninstagram.com/vp/29b9a8617a1825eb4f9dfa487a5ce9b9/5D31EC69/t51.2885-15/e35/14334437_1138232956264149_2486178287856910336_n.jpg?_nc_ht=scontent-sin6-2.cdninstagram.com&_nc_cat=109"
        ],
        "hashtags": [
            "wifeyforlifeycorettaandbrian",
            "weddingday"
        ],
        "comments": [
            {
                "comment": "Looking great Pash$ !!!",
                "author": "xo_cvl_xo"
            }
        ],
        "datetime": "2016-09-25T20:27:42.000Z",
        "caption": "What a fantastic wedding for a beautiful couple! So glad I could be there to witness it. #wifeyforlifeycorettaandbrian #weddingday",
        "likes": 13,
        "key": "https://www.instagram.com/p/BKytQrrgTGX/"
    },
    {
        "img_urls": [
            "https://scontent-sin6-2.cdninstagram.com/vp/3b112245904d4e53405ac878078aa264/5D76DD03/t51.2885-15/e35/14295341_643644085801675_971312638_n.jpg?_nc_ht=scontent-sin6-2.cdninstagram.com&_nc_cat=107"
        ],
        "hashtags": [
            "COlife",
            "fallfoilage",
            "lakedillon"
        ],
        "datetime": "2016-09-18T21:23:54.000Z",
        "caption": "They call me mellow yellow...#COlife #fallfoilage #lakedillon",
        "likes": 8,
        "key": "https://www.instagram.com/p/BKgyIHFg8ZL/"
    },
    {
        "img_urls": [
            "https://scontent-sin6-2.cdninstagram.com/vp/754735584bf14d646175a4314cb30c95/5D36A5CC/t51.2885-15/e35/13402422_481491952056174_1057493475_n.jpg?_nc_ht=scontent-sin6-2.cdninstagram.com&_nc_cat=106"
        ],
        "hashtags": [
            "womancard",
            "makedonalddrumpfagain"
        ],
        "datetime": "2016-06-16T23:54:25.000Z",
        "caption": "Now that I have my #womancard can I run for President? #makedonalddrumpfagain",
        "likes": 7,
        "key": "https://www.instagram.com/p/BGvAoSarAEX/"
    },
    {
        "img_urls": [
            "https://scontent-sin6-2.cdninstagram.com/vp/6477c47c31bb3227476696c6380f9678/5D5195AB/t51.2885-15/e35/13266877_257254261301069_1714492602_n.jpg?_nc_ht=scontent-sin6-2.cdninstagram.com&_nc_cat=105"
        ],
        "hashtags": [
            "santafeart"
        ],
        "datetime": "2016-05-30T19:33:51.000Z",
        "caption": "Just before the cop car rolled by... these two! #santafeart",
        "likes": 3,
        "key": "https://www.instagram.com/p/BGCxS_hrAPD/"
    },
    {
        "img_urls": [
            "https://scontent-sin6-2.cdninstagram.com/vp/f0032edb2324951cdc1345d16bd5129a/5D454206/t51.2885-15/e35/13249670_963393483775522_50463633_n.jpg?_nc_ht=scontent-sin6-2.cdninstagram.com&_nc_cat=110"
        ],
        "hashtags": [
            "fancyfriday",
            "photoboothfun",
            "lbd"
        ],
        "datetime": "2016-05-21T15:58:45.000Z",
        "caption": "Fun times at #fancyfriday #photoboothfun #lbd",
        "likes": 9,
        "key": "https://www.instagram.com/p/BFrNhsMLAAp/"
    },
    {
        "img_urls": [
            "https://scontent-sin6-2.cdninstagram.com/vp/9e18852d084b71019bc2dc70432462c3/5D70BFC6/t51.2885-15/e35/13116721_1125588674128518_1933262486_n.jpg?_nc_ht=scontent-sin6-2.cdninstagram.com&_nc_cat=106"
        ],
        "hashtags": [
            "hatscanbegnomes",
            "makedonalddrumpfagain",
            "travelbuddy",
            "hatsofinstagram"
        ],
        "datetime": "2016-04-28T23:45:52.000Z",
        "caption": "Oh hai. I'm @Pashmina's new gnome. You will find me in odd and random places over the next few months. I just got unboxed right here! #hatscanbegnomes #makedonalddrumpfagain #travelbuddy #hatsofinstagram",
        "likes": 7,
        "key": "https://www.instagram.com/p/BEw0sx_rABd/",
        "mentions": [
            "Pashmina"
        ]
    },
    {
        "img_urls": [
            "https://scontent-sin6-2.cdninstagram.com/vp/789c4ac5431b1e9c94fcd796b298cb84/5D38EA78/t51.2885-15/e35/13117897_998225620214667_516933202_n.jpg?_nc_ht=scontent-sin6-2.cdninstagram.com&_nc_cat=103"
        ],
        "hashtags": [
            "denver",
            "whatrooftop",
            "whatdeck"
        ],
        "comments": [
            {
                "comment": "Your new place?? Sweet view 🙌🏻",
                "author": "kristinlangenfeld"
            }
        ],
        "datetime": "2016-04-27T18:42:59.000Z",
        "caption": "Guess where I am? #denver #whatrooftop #whatdeck",
        "likes": 4,
        "key": "https://www.instagram.com/p/BEttPlGrAAz/"
    },
    {
        "img_urls": [
            "https://scontent-sin6-2.cdninstagram.com/vp/a7820662539dcf4939fe26a51aed6bff/5D52C00B/t51.2885-15/e35/12934975_1221511461199936_1847414272_n.jpg?_nc_ht=scontent-sin6-2.cdninstagram.com&_nc_cat=104"
        ],
        "hashtags": [
            "islandlife",
            "jamaica",
            "yaman",
            "toomanyfrozendrinks"
        ],
        "datetime": "2016-04-15T13:16:36.000Z",
        "caption": "Last night on the beach. #islandlife #jamaica #yaman #toomanyfrozendrinks",
        "likes": 6,
        "key": "https://www.instagram.com/p/BEOOWh8LAAD/"
    },
    {
        "img_urls": [
            "https://scontent-sin6-2.cdninstagram.com/vp/70ff10eb633ca8e479a62ae7466ff0c1/5D761C78/t51.2885-15/e35/12231006_621120798042654_336373067_n.jpg?_nc_ht=scontent-sin6-2.cdninstagram.com&_nc_cat=106"
        ],
        "hashtags": [
            "beachtime",
            "jamaica",
            "newfriends"
        ],
        "comments": [
            {
                "comment": "Those are my frands!!! @kathlynnsf @pashmina @_maryeh was just saying she wished she could join :) me too!",
                "mentions": [
                    "kathlynnsf",
                    "pashmina",
                    "_maryeh"
                ],
                "author": "xo_cvl_xo"
            }
        ],
        "datetime": "2016-04-11T03:05:55.000Z",
        "caption": "No filter needed! #beachtime #jamaica #newfriends",
        "likes": 10,
        "key": "https://www.instagram.com/p/BEC1SPsrAP5/"
    },
    {
        "caption": "Weird stuff at MCA.",
        "img_urls": [
            "https://scontent-sin6-2.cdninstagram.com/vp/bcc5e3df73d14f279f082ba8b88993ea/5D326C50/t51.2885-15/e35/12519553_987756787973970_882263538_n.jpg?_nc_ht=scontent-sin6-2.cdninstagram.com&_nc_cat=106"
        ],
        "likes": 9,
        "key": "https://www.instagram.com/p/BD_HCxLLABK/",
        "datetime": "2016-04-09T16:24:07.000Z"
    },
    {
        "img_urls": [
            "https://scontent-sin6-2.cdninstagram.com/vp/b876cfb78739d7126ad0046dadb3eb31/5D420EC0/t51.2885-15/e35/12965716_1388979037794291_911443104_n.jpg?_nc_ht=scontent-sin6-2.cdninstagram.com&_nc_cat=103"
        ],
        "hashtags": [
            "modernart",
            "blurry",
            "laughter"
        ],
        "datetime": "2016-04-09T03:34:55.000Z",
        "caption": "Good times. #modernart #blurry #laughter Couldn't stop shaking.",
        "likes": 7,
        "key": "https://www.instagram.com/p/BD9vA7xLAMn/"
    },
    {
        "caption": "Mara's baby shower!",
        "img_urls": [
            "https://scontent-sin6-2.cdninstagram.com/vp/2971a109064bfe7a549a71ee7b34b885/5D3E3E8B/t51.2885-15/e35/12783462_1706942726228584_230609892_n.jpg?_nc_ht=scontent-sin6-2.cdninstagram.com&_nc_cat=104"
        ],
        "likes": 6,
        "key": "https://www.instagram.com/p/BC3vmokLAEO/",
        "datetime": "2016-03-12T23:13:14.000Z"
    },
    {
        "img_urls": [
            "https://scontent-sin6-2.cdninstagram.com/vp/843dc7310dd2c4a24994da97b44fcd69/5D724F8B/t51.2885-15/e35/10864924_629355757205405_705429901_n.jpg?_nc_ht=scontent-sin6-2.cdninstagram.com&_nc_cat=105"
        ],
        "hashtags": [
            "volcanotime",
            "arenal",
            "puravida"
        ],
        "comments": [
            {
                "comment": "You have to check out the Natural hot springs in Arenal - it's beautiful and the water is amazing!",
                "author": "liveluvlaugh29"
            }
        ],
        "datetime": "2016-02-06T15:37:26.000Z",
        "caption": "Quick stop to stare at this for a bit and watch hummingbirds play. Then back to the beaches! #volcanotime #arenal #puravida",
        "likes": 10,
        "key": "https://www.instagram.com/p/BBcznoJrALu/"
    },
    {
        "img_urls": [
            "https://scontent-sin6-2.cdninstagram.com/vp/405d8096e4de40bcf534c3614eac1909/5D32CA7F/t51.2885-15/e35/12424709_554150074741979_91209948_n.jpg?_nc_ht=scontent-sin6-2.cdninstagram.com&_nc_cat=111"
        ],
        "hashtags": [
            "workisplay",
            "lovewhatyoudo",
            "cacaofarm",
            "chocorushco"
        ],
        "comments": [
            {
                "comment": "Very cool Pash!!!",
                "author": "kristinlangenfeld"
            }
        ],
        "datetime": "2016-02-01T20:32:35.000Z",
        "caption": "Visiting Finca La Amistad cacao farm was such a great experience. On the top we're \"massaging\" cacao beans as part of drying process. #workisplay #lovewhatyoudo #cacaofarm #chocorushco",
        "likes": 8,
        "key": "https://www.instagram.com/p/BBQdbDqrAJw/"
    },
    {
        "img_urls": [
            "https://scontent-sin6-2.cdninstagram.com/vp/4abbe3aa4f1eebc648b9c7eeb2a37e01/5D41C6B5/t51.2885-15/e35/12523559_1238592116170857_621650620_n.jpg?_nc_ht=scontent-sin6-2.cdninstagram.com&_nc_cat=109"
        ],
        "hashtags": [
            "cloudforest"
        ],
        "comments": [
            {
                "comment": "Awesome picture Pash!",
                "author": "marisaannm"
            },
            {
                "comment": "I went horse back riding in the cloud forests of Monteverde when I was there! Absolutely stunning - glad you are enjoying your time there :)",
                "author": "liveluvlaugh29"
            }
        ],
        "datetime": "2016-02-01T00:31:24.000Z",
        "caption": "The forest made me really happy. It's so beautiful! #cloudforest",
        "likes": 20,
        "key": "https://www.instagram.com/p/BBOT9SRLAAA/"
    },
    {
        "img_urls": [
            "https://scontent-sin6-2.cdninstagram.com/vp/f9b41e3d61a9511e692c4ed10add0700/5D3519D2/t51.2885-15/e35/12677662_1088621957823639_1871820052_n.jpg?_nc_ht=scontent-sin6-2.cdninstagram.com&_nc_cat=103"
        ],
        "hashtags": [
            "middaycoffeebreak"
        ],
        "comments": [
            {
                "comment": "We lived visiting that site in April! Loved CR!",
                "author": "clangpen"
            }
        ],
        "datetime": "2016-01-31T16:31:43.000Z",
        "caption": "Decided to get out of the clutches of beautiful Nosara and head towards other parts of Costa Rica. Glad I did! What a great view with my midday cup of coffee! And best coffee.I've had here too. #middaycoffeebreak",
        "likes": 7,
        "key": "https://www.instagram.com/p/BBNdD8lrABR/"
    },
    {
        "img_urls": [
            "https://scontent-sin6-2.cdninstagram.com/vp/f76b33170030d3d5228dfc38c6942ad8/5D586AF7/t51.2885-15/e35/12543275_698558433615118_1475426505_n.jpg?_nc_ht=scontent-sin6-2.cdninstagram.com&_nc_cat=110"
        ],
        "hashtags": [
            "Broncoswin",
            "beachonbeachonbeach",
            "sunsetsofinstagram",
            "sunsetsonthebeach"
        ],
        "datetime": "2016-01-25T20:54:44.000Z",
        "caption": "Never gets old. Even the sky bled orange for #Broncoswin yesterday! 😄 #beachonbeachonbeach #sunsetsofinstagram #sunsetsonthebeach",
        "likes": 3,
        "key": "https://www.instagram.com/p/BA-eZG3rAHT/"
    },
    {
        "img_urls": [
            "https://scontent-sin6-2.cdninstagram.com/vp/ab5e5607bcf66a2a8ca2ce2c01cfe8ea/5D38C9F5/t51.2885-15/e35/12424471_1082207428491412_1516207047_n.jpg?_nc_ht=scontent-sin6-2.cdninstagram.com&_nc_cat=104"
        ],
        "hashtags": [
            "howdotheydoit",
            "costaricancoffee",
            "organicfarming",
            "highoncaffeine"
        ],
        "datetime": "2016-01-21T22:26:49.000Z",
        "caption": "Picking coffee beans. Workers only make $2 a basket. The coffee is dried and sold to a coop for $7/lb. #howdotheydoit #costaricancoffee #organicfarming #highoncaffeine",
        "likes": 7,
        "key": "https://www.instagram.com/p/BA0VwFZrAI-/"
    },
    {
        "img_urls": [
            "https://scontent-sin6-2.cdninstagram.com/vp/024e25492ed386ae5f385126e3fe3c9f/5D53ED34/t51.2885-15/e35/917899_115083145539897_1085355811_n.jpg?_nc_ht=scontent-sin6-2.cdninstagram.com&_nc_cat=109"
        ],
        "hashtags": [
            "rawfooddiet",
            "camerashy",
            "mondays"
        ],
        "comments": [
            {
                "comment": "For some reason I ran into you in my dreams last night....maybe because I was hanging out in Sunnyside:) either way, when I saw this picture of you still in CR it took me a minute . Random!",
                "author": "alysa_paige"
            },
            {
                "comment": "@alysa_paige maybe its a sign you need to come join me! 😊",
                "mentions": [
                    "alysa_paige"
                ],
                "author": "pashmina"
            }
        ],
        "datetime": "2016-01-18T17:09:33.000Z",
        "caption": "Staging a pic of #rawfooddiet for @chocorushco requires standing on chairs. #camerashy #mondays",
        "likes": 7,
        "key": "https://www.instagram.com/p/BAsDDxGrAOT/",
        "mentions": [
            "chocorushco"
        ]
    },
    {
        "img_urls": [
            "https://scontent-sin6-2.cdninstagram.com/vp/67d722baff0a4ae7dfdaf176870b6a6e/5D564711/t51.2885-15/e35/12523664_786568811478184_867797222_n.jpg?_nc_ht=scontent-sin6-2.cdninstagram.com&_nc_cat=104"
        ],
        "hashtags": [
            "nofilter",
            "magicalplaces",
            "beachonbeachonbeach",
            "sunsetsonbeaches",
            "puravida"
        ],
        "comments": [
            {
                "comment": "Ahhhhh! So glad you made it!!! <3",
                "author": "karinka_mia"
            },
            {
                "comment": "Text me when you're ready to explore more .. Xx",
                "author": "karinka_mia"
            }
        ],
        "datetime": "2016-01-15T00:23:53.000Z",
        "caption": "Beautiful sunsets on beautiful beaches. And perfect place for ocean swimming! #nofilter #magicalplaces #beachonbeachonbeach #sunsetsonbeaches #puravida",
        "likes": 4,
        "key": "https://www.instagram.com/p/BAihlVDLAOH/"
    },
    {
        "img_urls": [
            "https://scontent-sin6-2.cdninstagram.com/vp/89a6727be107d88fe3c32b7b12dbefd5/5D55D60E/t51.2885-15/e35/12534129_717551721711321_684257_n.jpg?_nc_ht=scontent-sin6-2.cdninstagram.com&_nc_cat=109"
        ],
        "hashtags": [
            "floraandfauna",
            "wildlife",
            "puravida"
        ],
        "comments": [
            {
                "comment": "Enjoy that awesome country! #PuraVida I'm in your home state. 🎿❄",
                "hashtags": [
                    "PuraVida"
                ],
                "author": "curlysonita"
            }
        ],
        "datetime": "2016-01-14T20:45:57.000Z",
        "caption": "Another day in jungle paradise. More #floraandfauna and #wildlife than you can shake a fist at. #puravida PS. The howler monkeys are in a mood today",
        "likes": 10,
        "key": "https://www.instagram.com/p/BAiIpHrrANe/"
    },
    {
        "img_urls": [
            "https://scontent-sin6-2.cdninstagram.com/vp/23264da8a34848858d79e68e9806145f/5D5659D3/t51.2885-15/e35/12407709_1068004869917069_321074262_n.jpg?_nc_ht=scontent-sin6-2.cdninstagram.com&_nc_cat=105"
        ],
        "hashtags": [
            "sunsetsonbeaches",
            "volcanicash",
            "blacksandbeach",
            "sunsetsofinstagram",
            "puravida"
        ],
        "comments": [
            {
                "comment": "Miss you. Jealous!",
                "author": "xo_cvl_xo"
            }
        ],
        "datetime": "2016-01-14T00:43:00.000Z",
        "caption": "Just down the road from the resort. Volcanic ash feels like baby powder. #sunsetsonbeaches #volcanicash #blacksandbeach #sunsetsofinstagram #puravida",
        "likes": 5,
        "key": "https://www.instagram.com/p/BAf--ioLAOm/"
    },
    {
        "img_urls": [
            "https://scontent-sin6-2.cdninstagram.com/vp/8a34ca299ee8738f7ef1454fbd5fff6e/5D350DA0/t51.2885-15/e35/923589_835167836612189_1482129638_n.jpg?_nc_ht=scontent-sin6-2.cdninstagram.com&_nc_cat=105"
        ],
        "hashtags": [
            "Austin"
        ],
        "datetime": "2016-01-01T23:33:42.000Z",
        "caption": "First day of 2016. On top of the world! Not really. Just #Austin.",
        "likes": 10,
        "key": "https://www.instagram.com/p/BAA9gbgLAJC/"
    },
    {
        "caption": "Love these girls!",
        "img_urls": [
            "https://scontent-sin6-2.cdninstagram.com/vp/b52614eb4b9d31ddb506d1aa8dd576ad/5D41DD68/t51.2885-15/e35/10561090_169847156707781_691110451_n.jpg?_nc_ht=scontent-sin6-2.cdninstagram.com&_nc_cat=105"
        ],
        "likes": 3,
        "key": "https://www.instagram.com/p/__OqpBrAGX/",
        "datetime": "2016-01-01T07:25:10.000Z"
    },
    {
        "img_urls": [
            "https://scontent-sin6-2.cdninstagram.com/vp/5e927e249522ea0f3c8ae9e5c4f857ce/5D340F41/t51.2885-15/e35/12331451_1632255377034764_436220021_n.jpg?_nc_ht=scontent-sin6-2.cdninstagram.com&_nc_cat=108"
        ],
        "comments": [
            {
                "comment": "Love that smile. 😀",
                "author": "suveerb"
            }
        ],
        "datetime": "2015-12-25T05:28:13.000Z",
        "caption": "Penguin hat I had for 2 minutes before it got stolen by @spiderpig74",
        "likes": 17,
        "key": "https://www.instagram.com/p/_s_t_3rAGn/",
        "mentions": [
            "spiderpig74"
        ]
    },
    {
        "img_urls": [
            "https://scontent-sin6-2.cdninstagram.com/vp/adf8c99efb2622e2a2db33e9b5624f85/5D5806CE/t51.2885-15/e35/12393922_1538117219846972_796349103_n.jpg?_nc_ht=scontent-sin6-2.cdninstagram.com&_nc_cat=108"
        ],
        "comments": [
            {
                "comment": "Beautiful baby in the safest hands..... tk care enjoy",
                "author": "coolhunk007"
            }
        ],
        "datetime": "2015-12-24T23:40:19.000Z",
        "caption": "Charlie's first Christmas! @kmcclement",
        "likes": 4,
        "key": "https://www.instagram.com/p/_sX59qLAN5/",
        "mentions": [
            "kmcclement"
        ]
    },
    {
        "img_urls": [
            "https://scontent-sin6-2.cdninstagram.com/vp/9d14b7e26ceaa977c2d076231cc187be/5D450579/t51.2885-15/e35/12338824_1515026732130441_2058202715_n.jpg?_nc_ht=scontent-sin6-2.cdninstagram.com&_nc_cat=109"
        ],
        "hashtags": [
            "denverconstruction",
            "homesweethome"
        ],
        "comments": [
            {
                "comment": "Wow!! Sweet-looks gorgeous! Welcome back too! Pop by this week??",
                "author": "kristinlangenfeld"
            },
            {
                "comment": "So exciting!!!!!",
                "author": "csg7210"
            }
        ],
        "datetime": "2015-12-23T01:39:56.000Z",
        "caption": "Progress. Getting excited! #denverconstruction #homesweethome",
        "likes": 11,
        "key": "https://www.instagram.com/p/_ncATiLAHU/"
    },
    {
        "img_urls": [
            "https://scontent-sin6-2.cdninstagram.com/vp/3b65e09dc83c5cfb501c4cc326fb345c/5D3E991C/t51.2885-15/e35/12299039_841837699248770_1248987069_n.jpg?_nc_ht=scontent-sin6-2.cdninstagram.com&_nc_cat=102"
        ],
        "hashtags": [
            "dathamtho",
            "turkeyday",
            "gobblegobble",
            "nofilter"
        ],
        "comments": [
            {
                "comment": "Hahaha #therealworldbreck",
                "hashtags": [
                    "therealworldbreck"
                ],
                "author": "amharrigan"
            }
        ],
        "datetime": "2015-11-27T04:37:45.000Z",
        "caption": "Late nite eating. #dathamtho #turkeyday #gobblegobble #nofilter Yum!",
        "likes": 8,
        "key": "https://www.instagram.com/p/-kzr5arAPW/"
    },
    {
        "img_urls": [
            "https://scontent-sin6-2.cdninstagram.com/vp/065b20ddfd9cdd869be455ff106af6c8/5D7375BC/t51.2885-15/e35/12237251_776275989167174_1563930785_n.jpg?_nc_ht=scontent-sin6-2.cdninstagram.com&_nc_cat=102"
        ],
        "comments": [
            {
                "comment": "You are so bonita!!!!",
                "author": "sameden212"
            }
        ],
        "datetime": "2015-11-22T22:25:35.000Z",
        "caption": "Birthday twins!!",
        "likes": 10,
        "key": "https://www.instagram.com/p/-Z16iVLANG/"
    },
    {
        "img_urls": [
            "https://scontent-sin6-2.cdninstagram.com/vp/b0a6838699501e73f267b70c72384ed3/5D372A40/t51.2885-15/e35/12132889_1641813362723865_216523960_n.jpg?_nc_ht=scontent-sin6-2.cdninstagram.com&_nc_cat=109"
        ],
        "hashtags": [
            "Broncos",
            "GBvsDEN",
            "footballsunday"
        ],
        "datetime": "2015-11-02T03:34:41.000Z",
        "caption": "First time at #Broncos game! #GBvsDEN #footballsunday",
        "likes": 7,
        "key": "https://www.instagram.com/p/9kUmE0rAMy/"
    },
    {
        "caption": "Kellee and I went \"grocery shopping\"",
        "img_urls": [
            "https://scontent-sin6-2.cdninstagram.com/vp/7d4de02bc4b2a2ec538f78f8f9b428bd/5D7350E6/t51.2885-15/e35/12105121_1642008542713565_829161663_n.jpg?_nc_ht=scontent-sin6-2.cdninstagram.com&_nc_cat=105"
        ],
        "likes": 5,
        "key": "https://www.instagram.com/p/9XnRVWrAKu/",
        "datetime": "2015-10-28T05:07:45.000Z"
    },
    {
        "img_urls": [
            "https://scontent-sin6-2.cdninstagram.com/vp/6a87a379b220e7e313344d89339587a1/5D3EFB92/t51.2885-15/e35/11313806_971300999592958_240818181_n.jpg?_nc_ht=scontent-sin6-2.cdninstagram.com&_nc_cat=110"
        ],
        "hashtags": [
            "aspen",
            "fallishere"
        ],
        "datetime": "2015-09-28T00:02:21.000Z",
        "caption": "Beautiful view from the campsite this weekend! #aspen #fallishere",
        "likes": 15,
        "key": "https://www.instagram.com/p/8J0eVnLAC8/"
    },
    {
        "img_urls": [
            "https://scontent-sin6-2.cdninstagram.com/vp/f4d2641908175cd3519fba110b809ae8/5D426192/t51.2885-15/e35/11261017_1484172798573485_775411645_n.jpg?_nc_ht=scontent-sin6-2.cdninstagram.com&_nc_cat=105"
        ],
        "hashtags": [
            "chocolateislife"
        ],
        "datetime": "2015-09-05T17:55:11.000Z",
        "caption": "Over at @tazachcolate hanging out with Suveer in Boston! #chocolateislife",
        "likes": 2,
        "key": "https://www.instagram.com/p/7Qg9yfLAHI/",
        "mentions": [
            "tazachcolate"
        ]
    },
    {
        "img_urls": [
            "https://scontent-sin6-2.cdninstagram.com/vp/e1ca963fc0159435bcb1361d54428cde/5D51AA1C/t51.2885-15/e35/11934846_123363201345489_373244063_n.jpg?_nc_ht=scontent-sin6-2.cdninstagram.com&_nc_cat=109"
        ],
        "hashtags": [
            "whysoserious",
            "churches",
            "nofilter",
            "40daysand40nights"
        ],
        "comments": [
            {
                "comment": "#nailedit",
                "hashtags": [
                    "nailedit"
                ],
                "author": "xo_cvl_xo"
            },
            {
                "comment": "TIME to get wild in Spain.....enjoy",
                "author": "coolhunk007"
            }
        ],
        "datetime": "2015-08-28T13:15:06.000Z",
        "caption": "We had to lighten up the mood somehow. #whysoserious #churches #nofilter #40daysand40nights",
        "likes": 4,
        "key": "https://www.instagram.com/p/67ajZUrALo/"
    },
    {
        "img_urls": [
            "https://scontent-sin6-2.cdninstagram.com/vp/0c7bf96fdc45cf4fab5f573d33a0c27a/5D360A86/t51.2885-15/e35/11374057_1469304633371150_583779111_n.jpg?_nc_ht=scontent-sin6-2.cdninstagram.com&_nc_cat=102"
        ],
        "hashtags": [
            "gothic",
            "architecture",
            "40daysand40nights",
            "cathedrals",
            "moon"
        ],
        "comments": [
            {
                "comment": "I love gaudi!!!!",
                "author": "karinka_mia"
            }
        ],
        "datetime": "2015-08-27T21:50:38.000Z",
        "caption": "On the way back from dinner. Can't wait to see more #gothic #architecture by day. #40daysand40nights #cathedrals #moon",
        "likes": 8,
        "key": "https://www.instagram.com/p/65wwdArANs/"
    },
    {
        "img_urls": [
            "https://scontent-sin6-2.cdninstagram.com/vp/9fce10131a471a47c3a60c5db9499213/5D718EA0/t51.2885-15/e35/11875506_1014459635252545_721722925_n.jpg?_nc_ht=scontent-sin6-2.cdninstagram.com&_nc_cat=101"
        ],
        "hashtags": [
            "festivals",
            "latomatina"
        ],
        "datetime": "2015-08-26T08:18:29.000Z",
        "caption": "Almost time.. That ham is definitely not getting caught. #festivals #latomatina",
        "likes": 7,
        "key": "https://www.instagram.com/p/61vBIsLAJH/"
    },
    {
        "img_urls": [
            "https://scontent-sin6-2.cdninstagram.com/vp/c666edb321c910391544b9f5949d75ff/5D3B1B87/t51.2885-15/e35/11809913_1679170045652085_1894378889_n.jpg?_nc_ht=scontent-sin6-2.cdninstagram.com&_nc_cat=109"
        ],
        "hashtags": [
            "downtime"
        ],
        "datetime": "2015-08-24T18:58:27.000Z",
        "caption": "Calm before the storm. Chilling in Mallorca beach. #downtime",
        "likes": 10,
        "key": "https://www.instagram.com/p/6xuqrirAA-/"
    },
    {
        "img_urls": [
            "https://scontent-sin6-2.cdninstagram.com/vp/6aae5bda2e4d8daa3b382a570349942f/5D454073/t51.2885-15/e35/11887095_603889406420264_1687142683_n.jpg?_nc_ht=scontent-sin6-2.cdninstagram.com&_nc_cat=108"
        ],
        "hashtags": [
            "Alhambra",
            "Granada"
        ],
        "datetime": "2015-08-18T22:58:34.000Z",
        "caption": "More prettiness from #Alhambra #Granada",
        "likes": 7,
        "key": "https://www.instagram.com/p/6itYEsrALV/"
    },
    {
        "img_urls": [
            "https://scontent-sin6-2.cdninstagram.com/vp/c32b1ab1c621ea4745eb9d6a3dda9c3d/5D3F7809/t51.2885-15/e35/11881791_1689615284593984_1313662938_n.jpg?_nc_ht=scontent-sin6-2.cdninstagram.com&_nc_cat=104"
        ],
        "hashtags": [
            "Alhambra",
            "nasridpalace",
            "mathematics",
            "geometry",
            "pattern"
        ],
        "comments": [
            {
                "comment": "Fuck yes Pash$",
                "author": "xo_cvl_xo"
            }
        ],
        "datetime": "2015-08-18T00:12:02.000Z",
        "caption": "Perfection. #Alhambra #nasridpalace #mathematics #geometry #pattern",
        "likes": 6,
        "key": "https://www.instagram.com/p/6gQ_RGLAAL/"
    },
    {
        "img_urls": [
            "https://scontent-sin6-2.cdninstagram.com/vp/89208750d5d647746ee2a5a60b8fda9f/5D369681/t51.2885-15/e35/11917849_1659155230962786_1766771909_n.jpg?_nc_ht=scontent-sin6-2.cdninstagram.com&_nc_cat=106"
        ],
        "hashtags": [
            "Granada",
            "Alhambra",
            "nofilter",
            "Spain",
            "adventure"
        ],
        "datetime": "2015-08-17T19:59:12.000Z",
        "caption": "The view from our rooftop patio in #Granada #Alhambra So beautiful. #nofilter #Spain #adventure @sun_rise_girl",
        "likes": 9,
        "key": "https://www.instagram.com/p/6f0DjTLAGw/",
        "mentions": [
            "sun_rise_girl"
        ]
    },
    {
        "img_urls": [
            "https://scontent-sin6-2.cdninstagram.com/vp/e67097c0d25099d71e64e9d21d188e46/5D3B4185/t51.2885-15/e35/11909912_1478427792454256_672242059_n.jpg?_nc_ht=scontent-sin6-2.cdninstagram.com&_nc_cat=108"
        ],
        "hashtags": [
            "competa"
        ],
        "comments": [
            {
                "comment": "Hooray!!! I hope it is AMAZING!",
                "author": "csg7210"
            }
        ],
        "datetime": "2015-08-16T17:13:26.000Z",
        "caption": "Day 2 #competa beautiful white washed town behind us. Moscato grapes everywhere.",
        "likes": 6,
        "key": "https://www.instagram.com/p/6c8SlOrAHu/"
    },
    {
        "img_urls": [
            "https://scontent-sin6-2.cdninstagram.com/vp/c0c923a958ea7933a509333cd3ea69cf/5D734113/t51.2885-15/e35/11259933_1096629437032308_77158554_n.jpg?_nc_ht=scontent-sin6-2.cdninstagram.com&_nc_cat=100"
        ],
        "hashtags": [
            "instarepost20"
        ],
        "datetime": "2015-07-18T03:24:19.000Z",
        "caption": "repost via @instarepost20 from @momarie_\nThis is our life. Thank you, @pashmina, for another wonderful evening! 🐟 @candis172 @csg7210 @fiessial @ique_ball @paulgranadillo @grantgm35 #instarepost20",
        "likes": 7,
        "key": "https://www.instagram.com/p/5QyWgBLAEA/",
        "mentions": [
            "instarepost20",
            "momarie_",
            "pashmina",
            "candis172",
            "csg7210",
            "fiessial",
            "ique_ball",
            "paulgranadillo",
            "grantgm35"
        ]
    },
    {
        "img_urls": [
            "https://scontent-sin6-2.cdninstagram.com/vp/09dd04034b53db8f885995b83122af31/5D473465/t51.2885-15/e35/1515723_429501300570507_2002793741_n.jpg?_nc_ht=scontent-sin6-2.cdninstagram.com&_nc_cat=103"
        ],
        "hashtags": [
            "Homer",
            "Alaska"
        ],
        "datetime": "2015-07-16T01:25:09.000Z",
        "caption": "Trolling for salmon in #Homer #Alaska",
        "likes": 11,
        "key": "https://www.instagram.com/p/5LbH9CrAKm/"
    },
    {
        "img_urls": [
            "https://scontent-sin6-2.cdninstagram.com/vp/92db9cad9945f35324ea60f6cef0b719/5D37A90E/t51.2885-15/e35/11356570_437777913061737_49103182_n.jpg?_nc_ht=scontent-sin6-2.cdninstagram.com&_nc_cat=109"
        ],
        "hashtags": [
            "yum",
            "freshfish",
            "lastfrontier"
        ],
        "comments": [
            {
                "comment": "That fish is almost as big as you!!",
                "author": "meganmurphy5280"
            },
            {
                "comment": "You caught all of those?!! Amazing!!",
                "author": "kristinlangenfeld"
            }
        ],
        "datetime": "2015-07-14T21:01:29.000Z",
        "caption": "The spoils from our fishing trip. #yum #freshfish #lastfrontier",
        "likes": 6,
        "key": "https://www.instagram.com/p/5IYJ92rAAN/"
    },
    {
        "img_urls": [
            "https://scontent-sin6-2.cdninstagram.com/vp/80349374c36116fcbb87719fb6ce9142/5D533CC0/t51.2885-15/e35/11325087_1623783064536034_1318370665_n.jpg?_nc_ht=scontent-sin6-2.cdninstagram.com&_nc_cat=110"
        ],
        "hashtags": [
            "lastfrontier"
        ],
        "datetime": "2015-07-13T20:57:19.000Z",
        "caption": "Can't stop looking at this beauty. Two glaciers coverging together in the Great Gorge, Denali, Alaska. #lastfrontier",
        "likes": 11,
        "key": "https://www.instagram.com/p/5Fy4i_rAMF/"
    },
    {
        "img_urls": [
            "https://scontent-sin6-2.cdninstagram.com/vp/2f6c951732a998d8c5e8feb7fe427e6c/5D43707E/t51.2885-15/e35/11426174_785532574899597_986239299_n.jpg?_nc_ht=scontent-sin6-2.cdninstagram.com&_nc_cat=109"
        ],
        "hashtags": [
            "kittiwakebirds",
            "hugewaterfall"
        ],
        "comments": [
            {
                "comment": "Looks awesome!!!",
                "author": "sbriansmith"
            },
            {
                "comment": "We were right next to it on kayaks! Simply incredible.",
                "author": "pashmina"
            }
        ],
        "datetime": "2015-07-13T20:24:37.000Z",
        "caption": "Glacier runoff with thousands of black legged #kittiwakebirds All those white dots are birds! #hugewaterfall Just to get a sense of scale waterfall 200+ ft",
        "likes": 4,
        "key": "https://www.instagram.com/p/5FvJF2LAEC/"
    },
    {
        "img_urls": [
            "https://scontent-sin6-2.cdninstagram.com/vp/8401e56f6f5d4987aa82b122d9fe5385/5D44F966/t51.2885-15/e35/923859_429203890600283_2050623637_n.jpg?_nc_ht=scontent-sin6-2.cdninstagram.com&_nc_cat=111"
        ],
        "hashtags": [
            "nofilter",
            "hottubtime",
            "unbelievable"
        ],
        "comments": [
            {
                "comment": "So stunning 😍😍",
                "author": "namratalaungani89"
            }
        ],
        "datetime": "2015-07-12T05:08:49.000Z",
        "caption": "WHAT???? My view for the night. Alaska is too beautiful for words. #nofilter #hottubtime #unbelievable",
        "likes": 6,
        "key": "https://www.instagram.com/p/5BhiozLAHw/"
    },
    {
        "img_urls": [
            "https://scontent-sin6-2.cdninstagram.com/vp/3fe5df96c0b6fe4a2fd43047c4d9081e/5D45036E/t51.2885-15/e35/11251181_102163273464816_1985067140_n.jpg?_nc_ht=scontent-sin6-2.cdninstagram.com&_nc_cat=100"
        ],
        "hashtags": [
            "mckinley",
            "lastfrontier"
        ],
        "datetime": "2015-07-11T00:46:38.000Z",
        "caption": "Amazing experience! #mckinley #lastfrontier",
        "likes": 15,
        "key": "https://www.instagram.com/p/4-evhcLAHL/"
    },
    {
        "caption": "One is a weed, one is deathly poisonous, and one is harmless and pretty.",
        "img_urls": [
            "https://scontent-sin6-2.cdninstagram.com/vp/d02e714687f987f0ff406f18f867cad9/5D38AA94/t51.2885-15/e35/11424582_1641550922726170_2104954441_n.jpg?_nc_ht=scontent-sin6-2.cdninstagram.com&_nc_cat=110"
        ],
        "likes": 6,
        "key": "https://www.instagram.com/p/4-E1UkLAGd/",
        "datetime": "2015-07-10T21:00:14.000Z"
    },
    {
        "img_urls": [
            "https://scontent-sin6-2.cdninstagram.com/vp/5faed9d60f7389df6f1f46b6e7504b89/5D44FF52/t51.2885-15/e35/11353496_299472973556325_389615968_n.jpg?_nc_ht=scontent-sin6-2.cdninstagram.com&_nc_cat=109"
        ],
        "hashtags": [
            "adventure",
            "nofilter",
            "teambuilding"
        ],
        "datetime": "2015-07-10T03:37:16.000Z",
        "caption": "Denali ATV #adventure coal mine #nofilter #teambuilding",
        "likes": 6,
        "key": "https://www.instagram.com/p/48NeVnLAJh/"
    },
    {
        "img_urls": [
            "https://scontent-sin6-2.cdninstagram.com/vp/d26b5e859f033f80d2cdf0b6ff92df4f/5D56B773/t51.2885-15/e35/11258065_746272142148910_600126420_n.jpg?_nc_ht=scontent-sin6-2.cdninstagram.com&_nc_cat=110"
        ],
        "hashtags": [
            "happyfourth",
            "mountrushmore",
            "roadtripusa"
        ],
        "datetime": "2015-07-04T22:54:14.000Z",
        "caption": "#happyfourth #mountrushmore #roadtripusa Yay for cool Presidents!",
        "likes": 16,
        "key": "https://www.instagram.com/p/4u1G-ELAH2/"
    },
    {
        "img_urls": [
            "https://scontent-sin6-2.cdninstagram.com/vp/3ed3e68f4bf816c691cec2c4cdf70284/5D34E690/t51.2885-15/e35/11426651_784811344969292_1701438864_n.jpg?_nc_ht=scontent-sin6-2.cdninstagram.com&_nc_cat=108"
        ],
        "hashtags": [
            "parade",
            "USA",
            "tractors"
        ],
        "datetime": "2015-07-04T17:11:33.000Z",
        "caption": "Happy 4th! #parade #USA #tractors",
        "likes": 3,
        "key": "https://www.instagram.com/p/4uN5H5LAMs/"
    },
    {
        "img_urls": [
            "https://scontent-sin6-2.cdninstagram.com/vp/7ee320a291de0fd4ec1defb95fa1c1d2/5D359E53/t51.2885-15/e35/11410465_1457057447945222_956091932_n.jpg?_nc_ht=scontent-sin6-2.cdninstagram.com&_nc_cat=102"
        ],
        "hashtags": [
            "visitallstates"
        ],
        "comments": [
            {
                "comment": "Brrrrr",
                "author": "alysa_paige"
            }
        ],
        "datetime": "2015-07-04T02:17:46.000Z",
        "caption": "Red moon! #visitallstates South Dakota chillin w/ @candis172",
        "likes": 2,
        "key": "https://www.instagram.com/p/4snm3oLACG/",
        "mentions": [
            "candis172"
        ]
    },
    {
        "img_urls": [
            "https://scontent-sin6-2.cdninstagram.com/vp/7a16a77463cff291b6354a74c680b1e7/5D56A16C/t51.2885-15/e35/11357874_444905389004824_1759198998_n.jpg?_nc_ht=scontent-sin6-2.cdninstagram.com&_nc_cat=104"
        ],
        "hashtags": [
            "roadtrippin",
            "roadtripusa"
        ],
        "datetime": "2015-07-04T02:13:19.000Z",
        "caption": "#roadtrippin #roadtripusa Such a cool place! @candis172",
        "likes": 4,
        "key": "https://www.instagram.com/p/4snGQIrABT/",
        "mentions": [
            "candis172"
        ]
    },
    {
        "img_urls": [
            "https://scontent-sin6-2.cdninstagram.com/vp/c0886fb7844d9e06134524e0a3c90187/5D58A017/t51.2885-15/e15/11377488_100541306958368_1790893388_n.jpg?_nc_ht=scontent-sin6-2.cdninstagram.com&_nc_cat=108"
        ],
        "hashtags": [
            "circle",
            "latergram"
        ],
        "datetime": "2015-06-23T14:37:50.000Z",
        "caption": "#circle #latergram",
        "likes": 4,
        "key": "https://www.instagram.com/p/4RnjlPrAAj/"
    },
    {
        "img_urls": [
            "https://scontent-sin6-2.cdninstagram.com/vp/6d42d84bd19b9c249d0f485e021701cf/5D48415F/t51.2885-15/e15/10932367_784616254985053_1220444554_n.jpg?_nc_ht=scontent-sin6-2.cdninstagram.com&_nc_cat=101"
        ],
        "hashtags": [
            "westwordmuisc"
        ],
        "datetime": "2015-06-21T18:09:03.000Z",
        "caption": "Robert Delong #westwordmuisc",
        "likes": 2,
        "key": "https://www.instagram.com/p/4M2I7RLALx/"
    },
    {
        "img_urls": [
            "https://scontent-sin6-2.cdninstagram.com/vp/99ff1a9ab75e24385c4e580fa97b4267/5D360E27/t51.2885-15/e15/11426457_121278784871294_292523749_n.jpg?_nc_ht=scontent-sin6-2.cdninstagram.com&_nc_cat=102"
        ],
        "hashtags": [
            "BowmantoZelie"
        ],
        "datetime": "2015-06-12T23:05:19.000Z",
        "caption": "Start of the bachelorette weekend. #BowmantoZelie",
        "likes": 5,
        "key": "https://www.instagram.com/p/32M48hLAF8/"
    },
    {
        "img_urls": [
            "https://scontent-sin6-2.cdninstagram.com/vp/450771fe13f0d0a34370f88afe92c22d/5D392F8C/t51.2885-15/e15/11379951_1440920219561618_1377365562_n.jpg?_nc_ht=scontent-sin6-2.cdninstagram.com&_nc_cat=102"
        ],
        "hashtags": [
            "chocolate",
            "nails",
            "black",
            "brown",
            "swirl"
        ],
        "comments": [
            {
                "comment": "Super proud and happy for you sis a big big hug and congratulations @pashmina lets look at brining to bombay soon...wl FT soon 😘😘",
                "mentions": [
                    "pashmina"
                ],
                "author": "namratalaungani89"
            }
        ],
        "datetime": "2015-06-10T22:57:18.000Z",
        "caption": "repost from @omg_its_jennyp\n#chocolate #nails to celebrate the birth of @chocorushco #black #brown #swirl @fluffbar",
        "likes": 5,
        "key": "https://www.instagram.com/p/3xCYaDrAGu/",
        "mentions": [
            "omg_its_jennyp",
            "chocorushco",
            "fluffbar"
        ]
    },
    {
        "img_urls": [
            "https://scontent-sin6-2.cdninstagram.com/vp/6093153dc4c05cdb26183a6f48d6d02f/5D3E515F/t51.2885-15/e15/11417277_725119840931499_1871299811_n.jpg?_nc_ht=scontent-sin6-2.cdninstagram.com&_nc_cat=103"
        ],
        "hashtags": [
            "nofilter"
        ],
        "comments": [
            {
                "comment": "That's what I'm sayin @gr8britt2000 !",
                "mentions": [
                    "gr8britt2000"
                ],
                "author": "milbear13"
            }
        ],
        "datetime": "2015-06-07T19:28:15.000Z",
        "caption": "Dogs . F150. #nofilter fun times.",
        "likes": 8,
        "key": "https://www.instagram.com/p/3o8EtNLAEF/"
    },
    {
        "img_urls": [
            "https://scontent-sin6-2.cdninstagram.com/vp/a39c9580be80959179bb5ad8a78b3891/5CBD1109/t51.2885-15/e15/11280154_958019970928871_430219663_n.jpg?_nc_ht=scontent-sin6-2.cdninstagram.com&_nc_cat=111"
        ],
        "hashtags": [
            "milehighhangout"
        ],
        "datetime": "2015-05-19T18:59:10.000Z",
        "caption": "3D selfie! #milehighhangout so much fun! @momarie_ @donkim000 @ique_ball @gr8britt2000 @jasontylers @learz13",
        "likes": 9,
        "key": "https://www.instagram.com/p/239pGErALZ/",
        "mentions": [
            "momarie_",
            "donkim000",
            "ique_ball",
            "gr8britt2000",
            "jasontylers",
            "learz13"
        ]
    },
    {
        "img_urls": [
            "https://scontent-sin6-2.cdninstagram.com/vp/b0dc1085ce1935ef42a62555c6080ba9/5D6FDEAA/t51.2885-15/e15/11256819_377003985816968_641299489_n.jpg?_nc_ht=scontent-sin6-2.cdninstagram.com&_nc_cat=108"
        ],
        "hashtags": [
            "milehighhangout"
        ],
        "datetime": "2015-05-18T01:17:56.000Z",
        "caption": "Day at the beach. #milehighhangout",
        "likes": 12,
        "key": "https://www.instagram.com/p/2zfZgjrAJm/"
    },
    {
        "img_urls": [
            "https://scontent-sin6-2.cdninstagram.com/vp/6804d139c5af98e7e52ccc798db133c8/5D559888/t51.2885-15/e15/11243542_1388270024836945_295595868_n.jpg?_nc_ht=scontent-sin6-2.cdninstagram.com&_nc_cat=101"
        ],
        "hashtags": [
            "milehighhangout",
            "nofilter"
        ],
        "comments": [
            {
                "comment": "Are you in FL?!",
                "author": "karinka_mia"
            },
            {
                "comment": "Alabama",
                "author": "pashmina"
            }
        ],
        "datetime": "2015-05-17T23:05:44.000Z",
        "caption": "Look at those poses! #milehighhangout #nofilter",
        "likes": 8,
        "key": "https://www.instagram.com/p/2zQRQGrALR/"
    },
    {
        "img_urls": [
            "https://scontent-sin6-2.cdninstagram.com/vp/0f49a94e8f116dc70925d3a2e729e020/5D46BCC5/t51.2885-15/e15/11283329_1567328040194673_1741357848_n.jpg?_nc_ht=scontent-sin6-2.cdninstagram.com&_nc_cat=109"
        ],
        "hashtags": [
            "milehighhangout"
        ],
        "datetime": "2015-05-17T15:15:04.000Z",
        "caption": "Day 2. #milehighhangout",
        "likes": 3,
        "key": "https://www.instagram.com/p/2yaZ7QLAK1/"
    },
    {
        "img_urls": [
            "https://scontent-sin6-2.cdninstagram.com/vp/702573264cbca0aab840615f35491d72/5D55DF91/t51.2885-15/e15/11261949_632933383474602_1967895969_n.jpg?_nc_ht=scontent-sin6-2.cdninstagram.com&_nc_cat=106"
        ],
        "hashtags": [
            "milehighhangout",
            "hangoutfest"
        ],
        "comments": [
            {
                "comment": "Love this!!",
                "author": "scaradeath"
            }
        ],
        "datetime": "2015-05-15T21:47:45.000Z",
        "caption": "Old school ferris wheel! #milehighhangout #hangoutfest",
        "likes": 8,
        "key": "https://www.instagram.com/p/2t9wROrAPy/"
    },
    {
        "img_urls": [
            "https://scontent-sin6-2.cdninstagram.com/vp/b34ccd122fabe6cc8a992720a86a40bc/5D47CC49/t51.2885-15/e15/11256352_1640599239495176_11112134_n.jpg?_nc_ht=scontent-sin6-2.cdninstagram.com&_nc_cat=108"
        ],
        "hashtags": [
            "milehighhangout"
        ],
        "datetime": "2015-05-15T02:40:36.000Z",
        "caption": "First night #milehighhangout",
        "likes": 5,
        "key": "https://www.instagram.com/p/2r6eX1LAM0/"
    },
    {
        "caption": "In love with this and CO 😙",
        "img_urls": [
            "https://scontent-sin6-2.cdninstagram.com/vp/1bca11e21f0b6fd215b52c7f7bfecff6/5D39A97F/t51.2885-15/e15/11191508_833695210042615_1198533683_n.jpg?_nc_ht=scontent-sin6-2.cdninstagram.com&_nc_cat=107"
        ],
        "likes": 4,
        "key": "https://www.instagram.com/p/2KXR2mrANP/",
        "datetime": "2015-05-02T01:58:07.000Z"
    },
    {
        "caption": "Messy dessert eating.",
        "img_urls": [
            "https://scontent-sin6-2.cdninstagram.com/vp/6f174af954ac2a248033ef64deb92394/5D57B846/t51.2885-15/e15/10311063_1653775251510075_1911429490_n.jpg?_nc_ht=scontent-sin6-2.cdninstagram.com&_nc_cat=103"
        ],
        "likes": 3,
        "key": "https://www.instagram.com/p/1H2X8drAEa/",
        "datetime": "2015-04-06T06:00:43.000Z"
    },
    {
        "img_urls": [
            "https://scontent-sin6-2.cdninstagram.com/vp/75f65cbf36f0a5cde11fed0248722935/5D74AA02/t51.2885-15/e15/11055763_776711545731548_2077686243_n.jpg?_nc_ht=scontent-sin6-2.cdninstagram.com&_nc_cat=108"
        ],
        "comments": [
            {
                "comment": "At least you have a great mani!",
                "author": "melanylynn"
            },
            {
                "comment": "@melanylynn oh that's always a given 😀",
                "mentions": [
                    "melanylynn"
                ],
                "author": "pashmina"
            },
            {
                "comment": "What happened? Nail game on point tho.... 😘😘",
                "author": "willedward85"
            },
            {
                "comment": "Ouch!! 💅 😄",
                "author": "8kati3"
            }
        ],
        "datetime": "2015-03-28T03:31:27.000Z",
        "caption": "So this happened. I'm such a dork sometimes.",
        "likes": 2,
        "key": "https://www.instagram.com/p/0waIvWrAGw/"
    },
    {
        "img_urls": [
            "https://scontent-sin6-2.cdninstagram.com/vp/402237b0b6105dd41572c4a0b59554ed/5D781DC7/t51.2885-15/e15/11018367_344397442432905_1662764737_n.jpg?_nc_ht=scontent-sin6-2.cdninstagram.com&_nc_cat=109"
        ],
        "comments": [
            {
                "comment": "Remeber when you wanted to start a restaurant that only served eggs? And that one time you got super mad at the waiter because your eggs were undercooked? 😂😂😂 you do love your eggs. Miss you! 🍳🍳🍳😘",
                "author": "karinka_mia"
            },
            {
                "comment": "Over cooked and black!! Still want to do it. I think about that concept every time I am on the go. :)",
                "author": "pashmina"
            }
        ],
        "datetime": "2015-03-12T18:23:02.000Z",
        "caption": "My eggs made a heart! Yes eggs, I love you too.",
        "likes": 9,
        "key": "https://www.instagram.com/p/0Izc7RLAJE/"
    },
    {
        "img_urls": [
            "https://scontent-sin6-2.cdninstagram.com/vp/18fe9dc43c457df4cca57362d77e5739/5D5487C2/t51.2885-15/e15/11018454_1559447274322474_1243834482_n.jpg?_nc_ht=scontent-sin6-2.cdninstagram.com&_nc_cat=110"
        ],
        "datetime": "2015-03-09T00:08:40.000Z",
        "caption": "Mezcal overload this weekend. @Cochon555",
        "likes": 8,
        "key": "https://www.instagram.com/p/z_H03ArADA/",
        "mentions": [
            "Cochon555"
        ]
    },
    {
        "img_urls": [
            "https://scontent-sin6-2.cdninstagram.com/vp/e6d1c07c268f442330f74eb8b91785d2/5D384FFB/t51.2885-15/e15/11008137_1060839050599567_2077156880_n.jpg?_nc_ht=scontent-sin6-2.cdninstagram.com&_nc_cat=107"
        ],
        "hashtags": [
            "Repost",
            "jennypnails",
            "ifluff",
            "pink",
            "gelish",
            "glitter",
            "cute",
            "girly",
            "mani",
            "manicure",
            "goodgirlsgetnailed",
            "trendy",
            "fun",
            "denverbeauty",
            "5280"
        ],
        "datetime": "2015-02-14T20:20:04.000Z",
        "caption": "#Repost @omg_its_jennyp\n・・・\n#jennypnails #ifluff @fluffbar #pink #gelish #glitter #cute #girly #mani #manicure #goodgirlsgetnailed #trendy #fun #denverbeauty #5280 @cityofdenver",
        "likes": 0,
        "key": "https://www.instagram.com/p/zGELTkLAG2/",
        "mentions": [
            "omg_its_jennyp",
            "fluffbar",
            "cityofdenver"
        ]
    },
    {
        "img_urls": [
            "https://scontent-sin6-2.cdninstagram.com/vp/fd34b0a69d9b7af3ba757c5b66775241/5D753529/t51.2885-15/e15/10848376_632324346895999_856975132_n.jpg?_nc_ht=scontent-sin6-2.cdninstagram.com&_nc_cat=107"
        ],
        "comments": [
            {
                "comment": "Are you in town? Let's meet!!! Sending u my number on fb....",
                "author": "satnikify"
            }
        ],
        "datetime": "2014-12-27T14:20:29.000Z",
        "caption": "Beautiful sunset",
        "likes": 13,
        "key": "https://www.instagram.com/p/xHQExHLAEz/"
    },
    {
        "img_urls": [
            "https://scontent-sin6-2.cdninstagram.com/vp/11f7c7fb0b8e9f1653525cd325b9c33d/5D474294/t51.2885-15/e15/10844093_817308481643748_305793422_n.jpg?_nc_ht=scontent-sin6-2.cdninstagram.com&_nc_cat=100"
        ],
        "hashtags": [
            "dubai",
            "sandboarding"
        ],
        "comments": [
            {
                "comment": "Wow!!! Enjoy babe! 💋",
                "author": "karinka_mia"
            }
        ],
        "datetime": "2014-12-25T05:18:11.000Z",
        "caption": "Merry Christmas everyone! #dubai #sandboarding",
        "likes": 12,
        "key": "https://www.instagram.com/p/xBIbJVrAK6/"
    },
    {
        "img_urls": [
            "https://scontent-sin6-2.cdninstagram.com/vp/ce9eb664037be0ead7c0380f7ce7f287/5D481D79/t51.2885-15/e15/10838867_1565278027041737_1522553639_n.jpg?_nc_ht=scontent-sin6-2.cdninstagram.com&_nc_cat=105"
        ],
        "hashtags": [
            "onlyinindia"
        ],
        "comments": [
            {
                "comment": "Are u in Mumbai? Let me know of u free to meet up!",
                "author": "poojiu"
            },
            {
                "comment": "@poojiu hey! You live in B'bay now?? Had no idea. Been here a week or so, I leave in 24 hours but I'll be back in June! So definitely next trip! Which area do you stay? Been trekking between Colaba/Khar",
                "mentions": [
                    "poojiu"
                ],
                "author": "pashmina"
            },
            {
                "comment": "@pashmina ya hit me up when you're here next! Let's catch up. I'm in Bandra.",
                "mentions": [
                    "pashmina"
                ],
                "author": "poojiu"
            }
        ],
        "datetime": "2014-12-21T07:07:53.000Z",
        "caption": "Cook praying before he starts his day. Pretty substantial temple IN the restaurant kitchen. #onlyinindia",
        "likes": 4,
        "key": "https://www.instagram.com/p/w3BzHNLAHD/"
    },
    {
        "img_urls": [
            "https://scontent-sin6-2.cdninstagram.com/vp/dde77b0f2132a0566b1687ee8e2ff432/5D40B6EE/t51.2885-15/e15/928825_1556326107943993_2069637513_n.jpg?_nc_ht=scontent-sin6-2.cdninstagram.com&_nc_cat=101"
        ],
        "hashtags": [
            "colaba",
            "workanywhere"
        ],
        "datetime": "2014-12-18T10:47:02.000Z",
        "caption": "Drinks served in ceramic metal tusks. #colaba #workanywhere",
        "likes": 5,
        "key": "https://www.instagram.com/p/wvsflbrAHE/"
    },
    {
        "caption": "Mahak and Nikhils wedding",
        "img_urls": [
            "https://scontent-sin6-2.cdninstagram.com/vp/33233094fb944aa098e68beee0d99c70/5D767116/t51.2885-15/e15/1208256_1538058699767492_180939508_n.jpg?_nc_ht=scontent-sin6-2.cdninstagram.com&_nc_cat=108"
        ],
        "likes": 6,
        "key": "https://www.instagram.com/p/wtoeCvrAGF/",
        "datetime": "2014-12-17T15:33:23.000Z"
    },
    {
        "caption": "Had to do it. 1st selfie with the parents from Mahak's wedding.",
        "img_urls": [
            "https://scontent-sin6-2.cdninstagram.com/vp/c6d865f4e04fb6c71ba2313f46041f08/5D5709D6/t51.2885-15/e15/10860184_749024118510995_1653404569_n.jpg?_nc_ht=scontent-sin6-2.cdninstagram.com&_nc_cat=111"
        ],
        "likes": 8,
        "key": "https://www.instagram.com/p/wsox2YLACJ/",
        "datetime": "2014-12-17T06:16:51.000Z"
    },
    {
        "img_urls": [
            "https://scontent-sin6-2.cdninstagram.com/vp/027a5f3c10e580eea2637d300c818c6c/5D3A4CE4/t51.2885-15/e15/10809554_1554714154744730_1222939243_n.jpg?_nc_ht=scontent-sin6-2.cdninstagram.com&_nc_cat=102"
        ],
        "hashtags": [
            "Godsowncountry",
            "breck"
        ],
        "datetime": "2014-11-28T19:31:36.000Z",
        "caption": "This view never gets old. #Godsowncountry #breck",
        "likes": 10,
        "key": "https://www.instagram.com/p/v9IoEzrADm/"
    },
    {
        "img_urls": [
            "https://scontent-sin6-2.cdninstagram.com/vp/770e035f7a5db7a77b968e616d4b079b/5D40E383/t51.2885-15/e15/10802484_862916960409742_844234378_n.jpg?_nc_ht=scontent-sin6-2.cdninstagram.com&_nc_cat=110"
        ],
        "hashtags": [
            "woot"
        ],
        "comments": [
            {
                "comment": "Happy birthday!",
                "author": "marisaannm"
            },
            {
                "comment": "Happy birthday!",
                "author": "marcuskwan"
            }
        ],
        "datetime": "2014-11-22T20:05:37.000Z",
        "caption": "Birthday bonus! #woot",
        "likes": 7,
        "key": "https://www.instagram.com/p/vtvv-GrADF/"
    },
    {
        "img_urls": [
            "https://scontent-sin6-2.cdninstagram.com/vp/feda8bb27093a8bda8bc694b07957fd1/5D74D441/t51.2885-15/e15/10707106_472271812913573_295272454_n.jpg?_nc_ht=scontent-sin6-2.cdninstagram.com&_nc_cat=105"
        ],
        "hashtags": [
            "dontgetstuck",
            "powpow"
        ],
        "datetime": "2014-11-15T18:51:04.000Z",
        "caption": "Is this really the first weekend?? #dontgetstuck #powpow",
        "likes": 14,
        "key": "https://www.instagram.com/p/vblp7fLAP1/"
    },
    {
        "img_urls": [
            "https://scontent-sin6-2.cdninstagram.com/vp/9b06037ca75a0886f485a823cfc58e3c/5D534073/t51.2885-15/e15/10175334_817625811633083_984377481_n.jpg?_nc_ht=scontent-sin6-2.cdninstagram.com&_nc_cat=111"
        ],
        "hashtags": [
            "foodporn"
        ],
        "datetime": "2014-11-15T01:18:34.000Z",
        "caption": "#foodporn ember Breckenridge!",
        "likes": 4,
        "key": "https://www.instagram.com/p/vZtNEwLADW/"
    },
    {
        "img_urls": [
            "https://scontent-sin6-2.cdninstagram.com/vp/8f32eecede18a8ceb5e33a88d15367f1/5D3C95CD/t51.2885-15/e15/10727328_705676832849883_1967862767_n.jpg?_nc_ht=scontent-sin6-2.cdninstagram.com&_nc_cat=103"
        ],
        "hashtags": [
            "ACLfest"
        ],
        "datetime": "2014-10-11T00:50:42.000Z",
        "caption": "#ACLfest Sam Smith sounds amazing",
        "likes": 3,
        "key": "https://www.instagram.com/p/t_iMXBLAGF/"
    },
    {
        "img_urls": [
            "https://scontent-sin6-2.cdninstagram.com/vp/f79ed1a65b123c954d14185f78fd6b14/5D367905/t51.2885-15/e15/10684106_719618314742195_1936761734_n.jpg?_nc_ht=scontent-sin6-2.cdninstagram.com&_nc_cat=111"
        ],
        "hashtags": [
            "stamps",
            "wallpaper",
            "brooklyn"
        ],
        "comments": [
            {
                "comment": "Hey...sorry i missed you! I hope you had a blast😆",
                "author": "missmartin613"
            }
        ],
        "datetime": "2014-09-28T21:03:36.000Z",
        "caption": "#stamps #wallpaper #brooklyn",
        "likes": 4,
        "key": "https://www.instagram.com/p/tgOqnurADy/"
    },
    {
        "img_urls": [
            "https://scontent-sin6-2.cdninstagram.com/vp/395b856719f7de956b61b66d8a72b1f5/5D43BFFB/t51.2885-15/e15/1799785_449544875183218_1943780245_n.jpg?_nc_ht=scontent-sin6-2.cdninstagram.com&_nc_cat=110"
        ],
        "hashtags": [
            "BitchesGottaEat",
            "BGE"
        ],
        "datetime": "2014-09-21T02:23:29.000Z",
        "caption": "Another successful #BitchesGottaEat dinner! #BGE",
        "likes": 13,
        "key": "https://www.instagram.com/p/tMM6chrALj/"
    },
    {
        "img_urls": [
            "https://scontent-sin6-2.cdninstagram.com/vp/f4e5e1634e9293f57c81e7b0c8114a04/5D36F4D6/t51.2885-15/e15/10665635_682662331826438_870115457_n.jpg?_nc_ht=scontent-sin6-2.cdninstagram.com&_nc_cat=102"
        ],
        "comments": [
            {
                "comment": "I love Turks!!",
                "author": "marisaannm"
            }
        ],
        "datetime": "2014-09-01T15:25:41.000Z",
        "caption": "Docked",
        "likes": 7,
        "key": "https://www.instagram.com/p/saGiAjLAIQ/"
    }
]